nzshm_hazlab/__init__.py
nzshm_hazlab/base_functions.py
nzshm_hazlab/constants.py
nzshm_hazlab/data/__init__.py
nzshm_hazlab/data/data_loaders/__init__.py
nzshm_hazlab/data/data_loaders/data_loaders.py
nzshm_hazlab/data/data_loaders/dynamo_loader.py
nzshm_hazlab/data/data_loaders/oq_csv_loader.py
nzshm_hazlab/data/data_loaders/thp_loader.py
nzshm_hazlab/data/data_loaders/ths_loader.py
nzshm_hazlab/data/disaggregations.py
nzshm_hazlab/data/grids.py
nzshm_hazlab/data/hazard_curves.py
nzshm_hazlab/plot/__init__.py
nzshm_hazlab/plot/constants.py
nzshm_hazlab/plot/disaggregation.py
nzshm_hazlab/plot/hazard_curve.py
nzshm_hazlab/plot/hazard_map.py
nzshm_hazlab-0.1.1.dist-info/METADATA
nzshm_hazlab-0.1.1.dist-info/WHEEL
nzshm_hazlab-0.1.1.dist-info/licenses/LICENSE
nzshm_hazlab-0.1.1.dist-info/RECORD
