Metadata-Version: 2.4
Name: nzshm-hazlab
Version: 0.1.1
Summary: A laboratory for exploring hazard models
License-Expression: AGPL-3.0
License-File: LICENSE
Author: Chris DiCaprio
Author-email: christopher.dicaprio@gmail.com
Requires-Python: >=3.11,<3.13
Classifier: Programming Language :: Python :: 3
Classifier: Programming Language :: Python :: 3.11
Classifier: Programming Language :: Python :: 3.12
Provides-Extra: interactive
Requires-Dist: cartopy (>=0.24.1,<0.25.0)
Requires-Dist: ipython (>=9.9.0) ; extra == "interactive"
Requires-Dist: jupyterlab (>=4.5.2) ; extra == "interactive"
Requires-Dist: matplotlib (>=3.10.3,<4.0.0)
Requires-Dist: numpy (>=1.26.4,<2)
Requires-Dist: nzshm-common (<0.9.0)
Requires-Dist: nzshm-model (<0.14.0)
Requires-Dist: pandas (>=2.2.3,<3.0.0)
Requires-Dist: toshi-hazard-post (>=0.7.1,<0.8.0)
Requires-Dist: toshi-hazard-store (>=1.2.4,<2.0.0)
